django_htmx_partial_redirect/__init__.py
django_htmx_partial_redirect/middleware.py
django_htmx_partial_redirect-0.1.2.dist-info/METADATA
django_htmx_partial_redirect-0.1.2.dist-info/WHEEL
django_htmx_partial_redirect-0.1.2.dist-info/RECORD
