Metadata-Version: 2.1
Name: django-htmx-partial-redirect
Version: 0.1.2
Summary: `django-htmx-partial-redirect` is a middleware that redirects direct accesses to partial views (like login modals) to a full page, where the partial content is then lazy-loaded via HTMX, solving the issue of empty pages when accessing modal-intended views directly.
License: MIT
Author: Christian Tanul
Author-email: contact@tanulchristian.dev
Requires-Python: >=3.12,<4.0
Classifier: License :: OSI Approved :: MIT License
Classifier: Programming Language :: Python :: 3
Classifier: Programming Language :: Python :: 3.12
Requires-Dist: django (>=5.0.7,<6.0.0)
